eqlpy/__init__.py
eqlpy/eql_types.py
eqlpy/eqlalchemy.py
eqlpy-1.0.0.dist-info/METADATA
eqlpy-1.0.0.dist-info/WHEEL
eqlpy-1.0.0.dist-info/licenses/LICENSE
eqlpy-1.0.0.dist-info/RECORD
